MeiTingTrunk/_MainFrame.py
MeiTingTrunk/_MainFrameDataSlots.py
MeiTingTrunk/_MainFrameDocTableSlots.py
MeiTingTrunk/_MainFrameFilterListSlots.py
MeiTingTrunk/_MainFrameLibTreeSlots.py
MeiTingTrunk/_MainFrameLoadData.py
MeiTingTrunk/_MainFrameMetaTabSlots.py
MeiTingTrunk/_MainFrameOtherSlots.py
MeiTingTrunk/_MainFrameProperties.py
MeiTingTrunk/_MainFrameToolBarSlots.py
MeiTingTrunk/_MainWindow.py
MeiTingTrunk/__init__.py
MeiTingTrunk/main.py
MeiTingTrunk/resources.py
MeiTingTrunk/version.py
MeiTingTrunk/lib/__init__.py
MeiTingTrunk/lib/_crossref.py
MeiTingTrunk/lib/bibparse.py
MeiTingTrunk/lib/exportpdf.py
MeiTingTrunk/lib/import_mendeley.py
MeiTingTrunk/lib/pdfannotation.py
MeiTingTrunk/lib/retrievepdfmeta.py
MeiTingTrunk/lib/risparse.py
MeiTingTrunk/lib/sqlitedb.py
MeiTingTrunk/lib/sqlitefts.py
MeiTingTrunk/lib/tools.py
MeiTingTrunk/lib/xapiandb.py
MeiTingTrunk/lib/pdfjs/LICENSE
MeiTingTrunk/lib/pdfjs/build/pdf.js
MeiTingTrunk/lib/pdfjs/build/pdf.js.map
MeiTingTrunk/lib/pdfjs/build/pdf.worker.js
MeiTingTrunk/lib/pdfjs/build/pdf.worker.js.map
MeiTingTrunk/lib/pdfjs/web/compressed.tracemonkey-pldi-09.pdf
MeiTingTrunk/lib/pdfjs/web/debugger.js
MeiTingTrunk/lib/pdfjs/web/viewer.css
MeiTingTrunk/lib/pdfjs/web/viewer.html
MeiTingTrunk/lib/pdfjs/web/viewer.js
MeiTingTrunk/lib/pdfjs/web/viewer.js.map
MeiTingTrunk/lib/pdfjs/web/cmaps/78-EUC-H.bcmap
MeiTingTrunk/lib/pdfjs/web/cmaps/78-EUC-V.bcmap
MeiTingTrunk/lib/pdfjs/web/cmaps/78-H.bcmap
MeiTingTrunk/lib/pdfjs/web/cmaps/78-RKSJ-H.bcmap
MeiTingTrunk/lib/pdfjs/web/cmaps/78-RKSJ-V.bcmap
MeiTingTrunk/lib/pdfjs/web/cmaps/78-V.bcmap
MeiTingTrunk/lib/pdfjs/web/cmaps/78ms-RKSJ-H.bcmap
MeiTingTrunk/lib/pdfjs/web/cmaps/78ms-RKSJ-V.bcmap
MeiTingTrunk/lib/pdfjs/web/cmaps/83pv-RKSJ-H.bcmap
MeiTingTrunk/lib/pdfjs/web/cmaps/90ms-RKSJ-H.bcmap
MeiTingTrunk/lib/pdfjs/web/cmaps/90ms-RKSJ-V.bcmap
MeiTingTrunk/lib/pdfjs/web/cmaps/90msp-RKSJ-H.bcmap
MeiTingTrunk/lib/pdfjs/web/cmaps/90msp-RKSJ-V.bcmap
meitingtrunk-0.1a37.dist-info/LICENSE
meitingtrunk-0.1a37.dist-info/METADATA
meitingtrunk-0.1a37.dist-info/WHEEL
meitingtrunk-0.1a37.dist-info/entry_points.txt
meitingtrunk-0.1a37.dist-info/top_level.txt
meitingtrunk-0.1a37.dist-info/RECORD
