Metadata-Version: 2.1
Name: meitingtrunk
Version: 0.1a37
Summary: An open source reference management tool developed in PyQt5 and Python3.
Home-page: https://github.com/Xunius/MeiTingTrunk
Author: Guangzhi XU
Author-email: xugzhi1987@gmail.com
License: UNKNOWN
Platform: UNKNOWN
Classifier: Development Status :: 3 - Alpha
Classifier: Environment :: X11 Applications :: Qt
Classifier: Intended Audience :: End Users/Desktop
Classifier: License :: OSI Approved :: GNU General Public License v3 (GPLv3)
Classifier: Natural Language :: English
Classifier: Operating System :: POSIX :: Linux
Classifier: Operating System :: MacOS
Classifier: Programming Language :: Python :: 3
Classifier: Topic :: Education
Requires-Python: >=3
Requires-Dist: PyQt5 (>=5.12)
Requires-Dist: pdfminer.six
Requires-Dist: pypdf2
Requires-Dist: beautifulsoup4
Requires-Dist: fuzzywuzzy
Requires-Dist: bibtexparser
Requires-Dist: crossrefapi
Requires-Dist: RISparser
Requires-Dist: send2trash
Requires-Dist: python-levenshtein
Requires-Dist: PyQtWebEngine
